bulk_webp_url_replacer/__init__.py
bulk_webp_url_replacer/__main__.py
bulk_webp_url_replacer/cli.py
bulk_webp_url_replacer/etl_types.py
bulk_webp_url_replacer/extractor.py
bulk_webp_url_replacer/optimizer.py
bulk_webp_url_replacer/pipeline.py
bulk_webp_url_replacer-0.1.1.dist-info/METADATA
bulk_webp_url_replacer-0.1.1.dist-info/WHEEL
bulk_webp_url_replacer-0.1.1.dist-info/entry_points.txt
bulk_webp_url_replacer-0.1.1.dist-info/licenses/LICENSE
bulk_webp_url_replacer-0.1.1.dist-info/RECORD
