Metadata-Version: 2.4
Name: bulk-webp-url-replacer
Version: 0.1.1
Summary: Bulk convert images to WebP and automatically update URLs in markdown files
Project-URL: Homepage, https://github.com/HoangYell/bulk-webp-url-replacer
Project-URL: Repository, https://github.com/HoangYell/bulk-webp-url-replacer
Project-URL: Issues, https://github.com/HoangYell/bulk-webp-url-replacer/issues
Author-email: HoangYell <hoangyell@gmail.com>
License-Expression: MIT
License-File: LICENSE
Keywords: bulk,cdn,convert,images,markdown,optimization,replacer,url,webp
Classifier: Development Status :: 4 - Beta
Classifier: Intended Audience :: Developers
Classifier: License :: OSI Approved :: MIT License
Classifier: Programming Language :: Python :: 3
Classifier: Programming Language :: Python :: 3.9
Classifier: Programming Language :: Python :: 3.10
Classifier: Programming Language :: Python :: 3.11
Classifier: Programming Language :: Python :: 3.12
Classifier: Topic :: Text Processing :: Markup :: Markdown
Requires-Python: >=3.9
Requires-Dist: pillow>=9.0.0
Requires-Dist: requests>=2.25.0
